collie/__init__.py
collie/config.py
collie/module.py
collie/callbacks/__init__.py
collie/callbacks/callback.py
collie/callbacks/callback_manager.py
collie/callbacks/checkpoint_callback.py
collie/callbacks/has_monitor_callback.py
collie/callbacks/load_best_model_callback.py
collie/callbacks/topk_saver.py
collie/callbacks/utils.py
collie/controller/__init__.py
collie/controller/evaluator.py
collie/controller/server.py
collie/controller/trainer.py
collie/controller/utils.py
collie/data/__init__.py
collie/data/batch_sampler.py
collie/data/dataloader.py
collie/data/dataset.py
collie/data/template_utils.py
collie/driver/__init__.py
collie/driver/io/__init__.py
collie/driver/io/base.py
collie/driver/io/file.py
collie/driver/io/petrel.py
collie/log/__init__.py
collie/log/handler.py
collie/log/highlighter.py
collie/log/logger.py
collie/log/print.py
collie/metrics/__init__.py
collie/metrics/accuracy.py
collie/metrics/base.py
collie/metrics/bleu.py
collie/metrics/classify_f1_pre_rec_metric.py
collie/metrics/decode.py
collie/metrics/ppl.py
collie/metrics/rouge.py
collie/models/__init__.py
collie/models/base.py
collie/models/utils.py
collie/models/chatglm/__init__.py
collie/models/chatglm/model.py
collie/models/chatglm2/__init__.py
collie/models/chatglm2/model.py
collie/models/internlm/__init__.py
collie/models/internlm/model.py
collie/models/internlm2/__init__.py
collie/models/internlm2/configuration_internlm2.py
collie/models/internlm2/model.py
collie/models/llama/__init__.py
collie/models/llama/model.py
collie/models/moss/__init__.py
collie/models/moss/model.py
collie/models/moss_moon/__init__.py
collie/models/moss_moon/model.py
collie/models/moss_moon/utils.py
collie/optim/__init__.py
collie/optim/adalomo.py
collie/optim/adan.py
collie/optim/lion.py
collie/optim/lomo.py
collie/optim/sophiag.py
collie/utils/__init__.py
collie/utils/data_provider.py
collie/utils/dist_utils.py
collie/utils/metric_wrapper.py
collie/utils/monitor.py
collie/utils/padder.py
collie_lm-1.0.7.dist-info/LICENSE
collie_lm-1.0.7.dist-info/METADATA
collie_lm-1.0.7.dist-info/WHEEL
collie_lm-1.0.7.dist-info/entry_points.txt
collie_lm-1.0.7.dist-info/top_level.txt
collie_lm-1.0.7.dist-info/RECORD
