Metadata-Version: 2.1
Name: collie-lm
Version: 1.0.7
Summary: CoLLiE: Collaborative Training of Large Language Models in an Efficient Way
Author: OpenLMLab
Author-email: yanhang@pjlab.org.cn
Requires-Python: >=3.8
License-File: LICENSE
Requires-Dist: deepspeed >=0.10.0
Requires-Dist: tqdm
Requires-Dist: torch >=1.13.0
Requires-Dist: einops
Requires-Dist: transformers >=4.30.2
Requires-Dist: sentencepiece
Requires-Dist: protobuf ==3.20.1
Requires-Dist: websockets
Requires-Dist: fastapi
Requires-Dist: megatron-core ==0.2.0
Requires-Dist: tensorboard
Requires-Dist: google
Requires-Dist: peft
Requires-Dist: wandb
Requires-Dist: pandas
Requires-Dist: psutil
Requires-Dist: accelerate >=0.20.3
Requires-Dist: bitsandbytes >=0.41.0
Requires-Dist: scipy
Requires-Dist: rich >=13.3.5
Requires-Dist: safetensors
